Workbook

Sheet Summary
A1: MowDirect — Monthly Cost Report | May 2026
A3: Metric | B3: Amount (£) | C3: % of Net Revenue | D3: Notes
A4: Net Revenue (all channels, ex-VAT) | B4: ='Marketplace Fees & Commissions'!D20 -> 244331.12 | C4: =IFERROR(B4/B4,0) -> 1 | D4: Shopify Direct + eBay + Amazon + ManoMano + OnBuy + B&Q
A6: Marketplace commissions & fees | B6: ='Marketplace Fees & Commissions'!C20 -> 15738.67 | C6: =IFERROR(B6/B4,0) -> 0.064415331 | D6: Referral fees, subscriptions, listing charges — see Marketplace Fees tab
A7: Commission paid to Wayne Theisinger | B7: 9120.47 | C7: =IFERROR(B7/B4,0) -> 0.037328319 | D7: Post Audit – Actual Invoiced Amount
A8: Total paid ad spend | B8: ='Ad Spend'!C6 -> 11786.06 | C8: =IFERROR(B8/B4,0) -> 0.048238063 | D8: Google Ads + eBay Promoted Listings
A10: Total deductions (fees + commission + ads) | B10: =B6+B7+B8 -> 36645.2 | C10: =IFERROR(B10/B4,0) -> 0.14998171 | D10: All costs combined
A11: Contribution after deductions | B11: =B4-B10 -> 207685.92 | C11: =IFERROR(B11/B4,0) -> 0.85001829 | D11: Net revenue minus all marketplace costs.
A13: Commissions & Fees by Channel
A14: Channel | B14: Net Revenue (£) | C14: Commissions & Fees (£) | D14: Fee %
A15: Shopify Direct | B15: ='Marketplace Fees & Commissions'!D5 -> 130250.05 | C15: ='Marketplace Fees & Commissions'!C5 -> 2470.59 | D15: =IFERROR(C15/B15,0) -> 0.018968054
A16: eBay | B16: ='Marketplace Fees & Commissions'!D12 -> 7733.24 | C16: ='Marketplace Fees & Commissions'!C12 -> 907.23 | D16: =IFERROR(C16/B16,0) -> 0.11731564
A17: Amazon | B17: ='Marketplace Fees & Commissions'!D17 -> 24005.83 | C17: ='Marketplace Fees & Commissions'!C17 -> 4349.05 | D17: =IFERROR(C17/B17,0) -> 0.18116641
A18: B&Q (Mirakl) | B18: ='Marketplace Fees & Commissions'!D19 -> 82342 | C18: ='Marketplace Fees & Commissions'!C19 -> 8011.8 | D18: =IFERROR(C18/B18,0) -> 0.09729907
A19: TOTAL | B19: =SUM(B15:B18) -> 244331.12 | C19: =SUM(C15:C18) -> 15738.67 | D19: =IFERROR(C19/B19,0) -> 0.064415331
A21: Ad Spend by Platform
A22: Platform | B22: Spend (£) | C22: % of Net Revenue | D22: Note / Coverage
A23: Google Ads | B23: ='Ad Spend'!C4 -> 11786.06 | C23: =IFERROR(B23/B4,0) -> 0.048238063 | D23: COMPLETE
A24: eBay Promoted Listings | B24: 0 | C24: =IFERROR(B24/B4,0) -> 0 | D24: COMPLETE
A25: TOTAL | B25: =SUM(B23:B24) -> 11786.06 | C25: =IFERROR(B25/B4,0) -> 0.048238063

Sheet Marketplace Fees & Commissions
A1: Marketplace Commissions & Fees | May 2026
A3: Channel | B3: Fee Type | C3: Amount (£) | D3: Net Channel Revenue (£) | E3: Fee as % of Net Revenue | F3: Data Source | G3: Coverage
A4: Shopify Direct | B4: Payment processing fees | C4: 2470.59 | D4: 130250.05 | E4: =IFERROR(C4/D4,0) -> 0.018968054 | F4: Shopify GraphQL | G4: COMPLETE
A5: Shopify Direct subtotal | C5: =SUM(C4) -> 2470.59 | D5: =D4 -> 130250.05 | E5: =IFERROR(C5/D5,0) -> 0.018968054
A6: eBay | B6: Final value fees | C6: 1011.51 | D6: 7733.24 | E6: =IFERROR(C6/D6,0) -> 0.13080029 | F6: eBay Finances API | G6: COMPLETE
B7: Regulatory operating fee | C7: 32.48 | E7: =IFERROR(C7/D6,0) -> 0.0042000507
B8: Fixed per-order fee | C8: 2.8 | E8: =IFERROR(C8/D6,0) -> 0.00036207334
B9: Other eBay charges | C9: 27 | E9: =IFERROR(C9/D6,0) -> 0.0034914214
B10: Insertion fees | C10: 0.1 | E10: =IFERROR(C10/D6,0) -> 1.2931191e-05
B11: Fee credits (refunds from eBay) | C11: -166.66 | E11: =IFERROR(C11/D6,0) -> -0.021551122
A12: eBay subtotal | C12: =SUM(C6:C11) -> 907.23 | D12: =D6 -> 7733.24 | E12: =IFERROR(C12/D12,0) -> 0.11731564
A13: Amazon | B13: Commission | C13: 4164.93 | D13: 24005.83 | E13: =IFERROR(C13/D13,0) -> 0.1734966 | F13: SP-API Finances (Principal) · correct to: 29 May 2026 | G13: COMPLETE
B14: DigitalServicesFee | C14: 104.62 | E14: =IFERROR(C14/D13,0) -> 0.004358108
B15: RefundCommission | C15: 54.5 | E15: =IFERROR(C15/D13,0) -> 0.0022702818
B16: Subscription | C16: 25 | E16: =IFERROR(C16/D13,0) -> 0.0010414137
A17: Amazon subtotal | C17: =SUM(C13:C16) -> 4349.05 | D17: =D13 -> 24005.83 | E17: =IFERROR(C17/D17,0) -> 0.18116641
A18: B&Q (Mirakl) | B18: Commission | C18: 8011.8 | D18: 82342 | E18: =IFERROR(C18/D18,0) -> 0.09729907 | F18: Mirakl API | G18: COMPLETE
A19: B&Q (Mirakl) subtotal | C19: =SUM(C18) -> 8011.8 | D19: =D18 -> 82342 | E19: =IFERROR(C19/D19,0) -> 0.09729907
A20: GRAND TOTAL — MARKETPLACE FEES | C20: =C5+C12+C17+C19 -> 15738.67 | D20: =D5+D12+D17+D19 -> 244331.12 | E20: =IFERROR(C20/D20,0) -> 0.064415331
A22: ℹ Margin note — Amazon's referral fee is ~15% of GROSS (inc-VAT) sales, which works out to a HIGHER share of NET (ex-VAT) revenue — ~18-19%, as shown above. This is a real effect to be aware of: Amazon's effective cost against net revenue genuinely exceeds the 15% headline rate. It is surfaced here deliberately rather than masked. (Fees are already shown ex-VAT — the reclaimable 20% VAT Amazon charges on its fees has been removed.)

Sheet FBA Returns & Removals
A1: Amazon FBA — Returns, Removals & Stranded Stock | May 2026
A3: Customer Returns Received by Amazon
A4: Disposition | B4: Units | C4: Lines | D4: % of Returns | E4: Notes
A5: Unsellable — customer damaged | B5: 1 | C5: 1 | D5: =IFERROR(B5/B6,0) -> 1
A6: TOTAL CUSTOMER RETURNS | B6: =SUM(B5) -> 1 | C6: =SUM(C5) -> 1 | D6: =IFERROR(B6/B6,0) -> 1
A7: ↳ Returned to active inventory | B7: 0 | D7: =IFERROR(B7/B6,0) -> 0 | E7: Available for re-sale immediately.
A8: ↳ Stranded as unfulfillable | B8: 1 | D8: =IFERROR(B8/B6,0) -> 1 | E8: Sit at Amazon until removed, disposed of, or aged out.
A10: Removal Shipments (units processed by Amazon this month)
A11: Order Type | B11: Units | C11: Shipments | E11: Meaning
A12: Return | B12: 1 | C12: 1 | E12: Shipped back to MowDirect.
A13: TOTAL REMOVAL UNITS | B13: =SUM(B12) -> 1
A15: Removal & Disposal Costs (from Amazon Finances)
A16: Fee Type | B16: Amount (£) | E16: Notes
A17: FBA removal fees | B17: 36.63 | E17: Per-unit fee charged when removing stranded stock.
A18: TOTAL REMOVAL / DISPOSAL COST | B18: =SUM(B17) -> 36.63
A20: Current Inventory Snapshot — units sitting at Amazon today
A21: Bucket | B21: Units | E21: Meaning
A22: Fulfillable (sellable) | B22: 202 | E22: Active inventory available to ship to customers.
A23: Unfulfillable | B23: 0 | E23: Stranded — could be removed or disposed.
A24: Researching | B24: 0 | E24: Lost/damaged claims under investigation by Amazon.
A25: Inbound working | B25: 0 | E25: Shipment created in Seller Central but not yet sent.
A26: Inbound shipped | B26: 264 | E26: In transit from MowDirect/supplier to fulfilment centre.
A27: Inbound receiving | B27: 11 | E27: Arrived at FC, being checked in.
A28: AVAILABLE TO BE PICKED UP / DISPOSED | B28: =B23+B24 -> 0
A30: ℹ Inventory snapshot covers 28 active FBA SKUs at the time of report generation. Customer-returns and removal-shipment figures cover the reporting month only.

Sheet Cancellations
A1: Order Cancellations | May 2026
A3: Channel | B3: Reason / Attribution | C3: Orders | D3: Value (£) | E3: Notes / Coverage
A4: Shopify Direct | B4: Unknown | C4: 12 | D4: 4859.84 | E4: COMPLETE
B5: Customer | C5: 2 | D5: 706.67
A6: Shopify Direct subtotal | C6: =SUM(C4:C5) -> 14 | D6: =SUM(D4:D5) -> 5566.51
A7: Amazon | B7: Cancelled (attribution not exposed by SP-API; £ figure covers 1 of 15 orders) | C7: 15 | D7: 116.66 | E7: COMPLETE
A8: Amazon subtotal | C8: =SUM(C7) -> 15 | D8: =SUM(D7) -> 116.66
A9: B&Q (Mirakl) | B9: Customer-cancelled | C9: 4 | D9: 0 | E9: COMPLETE
A10: B&Q (Mirakl) subtotal | C10: =SUM(C9) -> 4 | D10: =SUM(D9) -> 0
A11: TOTAL CANCELLATIONS | C11: =C6+C8+C10 -> 33 | D11: =D6+D8+D10 -> 5683.17
A13: ℹ Direct channel APIs only — Shopify (cancelReason), Amazon SP-API (IsBuyerRequestedCancellation), Mirakl/B&Q (state). ManoMano, OnBuy and eBay cancellations are not yet covered.

Sheet Ad Spend
A1: Paid Ad Spend | May 2026
A3: Platform | B3: Campaign | C3: Spend (£) | D3: Conversions | E3: Conv. Value (£) | F3: Cost / Conv (£) | G3: ROAS | H3: Impressions | I3: Clicks | J3: CTR | K3: Coverage
A4: Google Ads | B4: Categories | PMax | CS | C4: 11786.06 | D4: 100.52 | E4: 79095.86 | F4: =IFERROR(C4/D4,0) -> 117.2509 | G4: =IFERROR(E4/C4,0) -> 6.710967 | H4: 1005339 | I4: 20108 | J4: =IFERROR(I4/H4,0) -> 0.020001214 | K4: COMPLETE
A6: TOTAL AD SPEND | C6: =C4 -> 11786.06 | D6: =D4 -> 100.52 | E6: =E4 -> 79095.86 | F6: =IFERROR(C6/D6,0) -> 117.2509 | G6: =IFERROR(E6/C6,0) -> 6.710967
A8: ℹ Showing campaigns with spend only. Conversions / Conv. Value / Cost-per-Conv / ROAS reflect Google Ads conversion tracking; eBay Promoted Listings does not yet feed conversion data into this report.

Sheet Raw Data
A1: Raw Data — Transactions | May 2026
A3: eBay Finance Transactions
A4: Transaction ID | B4: Date | C4: Type | D4: Amount (£) | E4: Order ID | F4: Source
A5: 10-14707-57595 | B5: 2026-05-31 | C5: SALE | D5: 1643.01 | E5: 10-14707-57595 | F5: eBay Finances API
A6: 20-14679-79480 | B6: 2026-05-28 | C6: SALE | D6: 1210.51 | E6: 20-14679-79480 | F6: eBay Finances API
A7: 13-14688-79237 | B7: 2026-05-27 | C7: SALE | D7: 1210.51 | E7: 13-14688-79237 | F7: eBay Finances API
A8: 17-14677-02970 | B8: 2026-05-26 | C8: SALE | D8: 328.18 | E8: 17-14677-02970 | F8: eBay Finances API
A9: 11-14684-46677 | B9: 2026-05-26 | C9: SALE | D9: 1210.51 | E9: 11-14684-46677 | F9: eBay Finances API
A10: 23-14657-96725 | B10: 2026-05-24 | C10: SALE | D10: 1210.51 | E10: 23-14657-96725 | F10: eBay Finances API
A11: 26-14652-90769 | B11: 2026-05-24 | C11: SALE | D11: 1210.51 | E11: 26-14652-90769 | F11: eBay Finances API
A12: FEE-8109165521911_11 | B12: 2026-05-21 | C12: NON_SALE_CHARGE | D12: 0.12 | E12: — | F12: eBay Finances API
A13: DISPUTE_HOLD_REVERSE-6671255098-6549824969 | B13: 2026-05-09 | C13: CREDIT | D13: 199.99 | E13: 04-14399-98099 | F13: eBay Finances API
A14: 24905182983 | B14: 2026-05-08 | C14: TRANSFER | D14: 1.8 | E14: — | F14: eBay Finances API
A15: INVOICE-8051230661111_11 | B15: 2026-05-01 | C15: NON_SALE_CHARGE | D15: 32.4 | E15: — | F15: eBay Finances API
A17: Amazon Settlement Line Items
A18: Settlement ID | B18: Posted Date | C18: Fee Type | D18: Amount (£) | E18: Order ID | F18: Source
B19: 2026-05-01T17:14:42Z | C19: Commission | D19: -35.99 | E19: 205-6979605-2383515 | F19: SP-API Finances (Shipment)
B20: 2026-05-01T17:14:42Z | C20: DigitalServicesFee | D20: -0.72 | E20: 205-6979605-2383515 | F20: SP-API Finances (Shipment)
B21: 2026-05-01T17:51:56Z | C21: FBAPerUnitFulfillmentFee | D21: -15.99 | E21: 202-4668783-3203504 | F21: SP-API Finances (Shipment)
B22: 2026-05-01T17:51:56Z | C22: Commission | D22: -36 | E22: 202-4668783-3203504 | F22: SP-API Finances (Shipment)
B23: 2026-05-01T17:51:56Z | C23: DigitalServicesFee | D23: -1.05 | E23: 202-4668783-3203504 | F23: SP-API Finances (Shipment)
B24: 2026-05-01T20:37:08Z | C24: Commission | D24: -37.46 | E24: 202-8129877-5077123 | F24: SP-API Finances (Shipment)
B25: 2026-05-01T20:37:08Z | C25: DigitalServicesFee | D25: -0.75 | E25: 202-8129877-5077123 | F25: SP-API Finances (Shipment)
B26: 2026-05-01T20:48:25Z | C26: FBAPerUnitFulfillmentFee | D26: -21 | E26: 205-3129033-4169965 | F26: SP-API Finances (Shipment)
B27: 2026-05-01T20:48:25Z | C27: Commission | D27: -36 | E27: 205-3129033-4169965 | F27: SP-API Finances (Shipment)
B28: 2026-05-01T20:48:25Z | C28: DigitalServicesFee | D28: -1.14 | E28: 205-3129033-4169965 | F28: SP-API Finances (Shipment)
B29: 2026-05-01T21:13:38Z | C29: FBAPerUnitFulfillmentFee | D29: -21 | E29: 206-1314824-4601121 | F29: SP-API Finances (Shipment)
B30: 2026-05-01T21:13:38Z | C30: Commission | D30: -36 | E30: 206-1314824-4601121 | F30: SP-API Finances (Shipment)
... B38: 2026-05-01T22:08:04Z | C38: Commission | D38: -36 | E38: 204-0183953-9580342 | F38: SP-API Finances (Shipment)
A40: Google Ads — Campaign Spend
A41: Campaign ID | B41: Type | C41: Campaign Name | D41: Spend (£) | E41: Impressions | F41: Clicks
A42: 22988998513 | B42: PERFORMANCE_MAX | C42: Categories | PMax | CS | D42: 11786.062 | E42: 1005339 | F42: 20108
